{"status":{"code":200,"http":"Fetched (ping) 200 3433 and parsed 1/60 entries","nextFetch":1505607,"entriesCountSinceLastMaintenance":19,"velocity":36,"popularity":3.1457879355245097,"generatedIds":true,"period":3433,"lastFetch":1505604,"lastParse":1505604,"lastMaintenanceAt":1505582,"feed":"http://feeds.sciencedaily.com/sciencedaily"},"permalinkUrl":"https://www.sciencedaily.com/news/","standardLinks":{"alternate":[{"title":"Latest Science News -- ScienceDaily","rel":"alternate","href":"https://www.sciencedaily.com/news/","type":"text/html"}],"image":[{"title":"Latest Science News -- ScienceDaily","rel":"image","href":"https://www.sciencedaily.com/images/scidaily-logo-rss.png","type":"image/png"}],"hub":[{"title":"","rel":"hub","href":"http://pubsubhubbub.appspot.com/","type":"text/html"}],"self":[{"title":"Latest Science News -- ScienceDaily","rel":"self","href":"http://www.sciencedaily.com/rss/newsfeed.xml","type":"application/rss+xml"}]},"image":"https://www.sciencedaily.com/images/scidaily-logo-rss.png","title":"Latest Science News -- ScienceDaily","updated":1505603641,"id":"latest-science-news-sciencedaily-2017-9-16-23","items":[{"id":"https://www.sciencedaily.com/releases/2017/09/170915095236.htm","published":1505483556,"updated":1505483556,"title":"Immigrant parents report fewer adverse childhood experiences than US-born parents","summary":"A new study found immigrants reported fewer potentially health-harming adverse childhood experiences, such as abuse, violence, or divorce, than native-born Americans. The findings suggest immigrants may experience different forms of stress early in life than do those born in the United States.","permalinkUrl":"https://www.sciencedaily.com/releases/2017/09/170915095236.htm","standardLinks":{"alternate":[{"title":"Immigrant parents report fewer adverse childhood experiences than US-born parents","rel":"alternate","href":"https://www.sciencedaily.com/releases/2017/09/170915095236.htm","type":"text/html"}]},"language":"en"}]}